{
  "occupation": "công_nghệ_thông_tin_kỹ_thuật_số / backend_developer",
  "core_skills": {
    "Java": 0.9723,
    "MySQL": 0.9231,
    "SQL": 0.8602,
    "REST API": 0.7859,
    "Lập trình": 0.7492,
    "JavaScript": 0.7397,
    "PostgreSQL": 0.7133,
    "Docker": 0.626,
    "Spring Boot": 0.6225,
    "MongoDB": 0.6038,
    "Git": 0.5979,
    "Oracle": 0.5402,
    "SQL Server": 0.4837,
    "Kubernetes": 0.4436,
    "Redis": 0.4333,
    "CSS": 0.4137,
    "Microservices": 0.4036,
    "Apache Kafka": 0.3941,
    "CI/CD": 0.3798,
    "Agile": 0.3742,
    "AWS": 0.3608,
    "HTML": 0.3549
  },
  "optional_skills": {
    "Go": 0.346,
    "DevOps": 0.3333,
    "PHP": 0.3286,
    "NoSQL": 0.3035,
    ".NET": 0.2961,
    "Scrum": 0.2808,
    "Python": 0.2709,
    "C#": 0.2434,
    "Node.js": 0.2304,
    "RabbitMQ": 0.23,
    "Hibernate": 0.224,
    "Jira": 0.2234,
    "Tư duy logic": 0.2217,
    "Machine Learning": 0.2132,
    "Google Cloud": 0.1982,
    "Linux": 0.1939,
    "Elasticsearch": 0.1855,
    "Azure": 0.1747,
    "Laravel": 0.1545,
    "Spring": 0.1528,
    "Angular": 0.1482,
    ".NET Core": 0.141,
    "NestJS": 0.1332,
    "MVC": 0.1291,
    "UI/UX": 0.1198,
    "Entity Framework": 0.1054,
    "Java Spring Boot": 0.1054,
    "Struts": 0.1054,
    "TypeScript": 0.1032,
    "GitLab": 0.1032,
    "Java Core": 0.0965,
    "Microservice": 0.0965,
    "GraphQL": 0.0865,
    "React.js": 0.0865,
    "GitHub": 0.0832,
    "CRM": 0.0806,
    "Web API": 0.0743,
    "ASP.NET": 0.0743,
    "OOP": 0.0743,
    "API": 0.0694,
    "Jenkins": 0.0659,
    "Mentoring": 0.0579,
    "Giao tiếp tiếng Anh": 0.0579,
    "Java EE": 0.0579,
    "Ruby": 0.0579,
    "ERP": 0.0565,
    "jQuery": 0.052,
    "WordPress": 0.052,
    "PL/SQL": 0.0481,
    "Postman": 0.0481,
    "Tư duy tốt": 0.0481,
    "Vue.js": 0.0453,
    "Phân tích dữ liệu": 0.0432,
    "Team player": 0.0342,
    ".NetCore": 0.0342,
    "Khả năng chịu áp lực cao": 0.0342,
    "CodeIgniter": 0.0342,
    "Spring MVC": 0.0342,
    "JSP": 0.0342,
    "JDBC": 0.0342,
    "Express.js": 0.0342,
    "Microservices architecture": 0.0342,
    "gRPC": 0.0342,
    "Web Service": 0.0342,
    "Spring Framework": 0.0342,
    "Good communication skills": 0.0298,
    "Kỹ năng làm việc theo nhóm": 0.0298,
    "Tư duy hệ thống": 0.0269,
    "Collaboration": 0.0269,
    "SVN": 0.0269,
    "FastAPI": 0.0269,
    "Django": 0.0269,
    "Bootstrap": 0.0269,
    "HTML5": 0.0269,
    "React": 0.0248,
    "Khả năng học hỏi": 0.0248,
    "Flask": 0.0248,
    "Figma": 0.0231,
    "Tuyển dụng": 0.0218,
    "HSM": 0.0105,
    "Ajax": 0.0105,
    "Khả năng tự học tốt": 0.0105,
    "Chịu được áp lực công việc cao": 0.0105,
    "IDE (Eclipse, IntelliJ, NetBeans)": 0.0105,
    "Team leadership": 0.0105,
    "Spring Security": 0.0105,
    "Nghiêm túc trong công việc": 0.0105,
    "Nắm vững kiến thức về cấu trúc dữ liệu và giải thuật": 0.0105,
    "REST": 0.0105,
    "Database (SQL, NoSQL)": 0.0105,
    "ASP.NET MVC": 0.0105,
    "Ruby on Rails": 0.0105,
    "OracleDB": 0.0105,
    "GORM": 0.0105,
    "CEPH": 0.0105,
    "API (REST API, SOAP)": 0.0105,
    "LINQ": 0.0105,
    "Socket TCP/IP": 0.0105,
    "GIN": 0.0105,
    "Apache Apache Kafka": 0.0105,
    "nginx": 0.0105,
    "Tư duy thiết kế hướng đối tượng": 0.0105,
    "Kỹ năng research": 0.0105,
    "Vert.x": 0.0105,
    "JPA": 0.0105,
    "SQL Query": 0.0105,
    "Tư duy giải quyết vấn đề": 0.0105,
    "SCM (Git, SVN)": 0.0105,
    "Spring Data": 0.0105,
    "Excellent problem-solving skills": 0.0105,
    "Bitbucket": 0.0105,
    "ClickHouse": 0.0105,
    "MinIO": 0.0105,
    "MariaDB": 0.0105,
    "OpenShift": 0.0105,
    "Lập trình hướng đối tượng": 0.0075,
    "Kubernetes (Kubernetes)": 0.0075,
    "Grafana": 0.0075,
    "React JavaScript": 0.0075,
    "C/C++": 0.0075,
    "Có trách nhiệm cao với công việc": 0.0075,
    "Chịu khó tìm tòi": 0.0075,
    "Kiểm thử tự động": 0.0075,
    "Khả năng phân tích": 0.0056,
    "Attention to detail": 0.0056,
    "Strong communication skills": 0.0056,
    "Confluence": 0.0056,
    "React Native": 0.0042,
    "SEO": 0.0042,
    "luật": 0.0042,
    "Kỹ năng phân tích": 0.0031
  },
  "responsibilities": [
    "Tham gia vào các dự án chuyển đổi kỹ thuật số của các khách hàng Smartosc trên toàn cầu. Dẫn dắt và quản lý một nhóm gồm hơn 15 nhà phát triển và nhân viên kỹ thuật trong một dự án toàn cầu. Giám sát thiết kế kỹ thuật và kiến trúc của các hệ thống phần mềm, đảm bảo khả năng mở rộng, bảo mật và hiệu suất. Phối hợp chặt chẽ với khách hàng để thu thập các yêu cầu, cung cấp các giải pháp và quản lý kỳ vọng kỹ thuật. Thực hiện đánh giá mã, cung cấp cố vấn cho các thành viên trong nhóm và thúc đẩy sự xuất sắc về kỹ thuật. Đảm bảo các cột mốc dự án và các sản phẩm giao hàng được đáp ứng đúng hạn và trong ngân sách. Phối hợp với các nhóm chức năng chéo bao gồm các nhà quản lý dự án, BA, người thử nghiệm và DevOps. Xác định các cơ hội để cải tiến quy trình và thúc đẩy các thực tiễn tốt nhất kỹ thuật. Luôn cập nhật với các xu hướng của ngành và các công nghệ mới nổi liên quan đến doanh nghiệp. Hỗ trợ triển khai giải pháp sau bán hàng (nếu cần) để đảm bảo thành công và sự hài lòng.",
    "Phân tích yêu cầu nghiệp vụ và tham gia thiết kế kiến trúc phần mềm theo hướng modular dễ mở rộng. \n Phát triển các API backend chuẩn REST API hoặc GraphQL phục vụ cho web/mobile. \n Tham gia thiết kế và quản lý cơ sở dữ liệu MySQL / CassandraDB. \n Tối ưu hóa hiệu suất và đảm bảo ứng dụng chạy mượt mà trên các môi trường khác nhau. \n Tối ưu hóa hiệu năng hệ thống, xử lý các bài toán về tốc độ truy vấn, memory và khả năng chịu tải cao. \n Tham gia viết unit test, integration test, và hỗ trợ kiểm thử tự động. \n Chủ động phát hiện và xử lý nợ kỹ thuật (technical debt), đề xuất refactor các phần code yếu. \n Viết tài liệu kỹ thuật và comment mã nguồn. \n Tham gia quản lý mã nguồn bằng các công cụ như Git, đảm bảo quy trình làm việc chuẩn và hiệu quả. \n Áp dụng các công nghệ tiên tiến để cải thiện chất lượng và hiệu suất của ứng dụng.",
    "Lập trình phát triển các dự án, sản phẩm lớn dựa trên nền tảng công nghệ, gồm: C#.NET, HTML5/JavaScript, WCF/REST-full, SQL Server Server/Oracle. Báo cáo công việc định kỳ cho trưởng nhóm. Trao đổi cụ thể trong quá trình phỏng vấn.",
    "Tham gia Trung tâm Đổi mới Công nghệ xuất sắc (COE) của chúng tôi tại Crossian, một công ty khởi nghiệp đang phát triển nhanh chóng đạt được cột mốc 100 triệu đô la vào năm 2024. Trong vai trò năng động này, bạn sẽ kiểm tra hàng ngày với nhóm của bạn để phù hợp với các mục tiêu dự án và hợp tác trên hệ thống sinh thái của chúng tôi với một tư duy nhanh nhẹn. Tham gia vào các trường hợp đặc tả kỹ thuật thử nghiệm trong quá trình phát triển Agile/Scrum. Phát triển mã sạch, có thể mở rộng bằng cách sử dụng .NET Core trong kiến trúc dịch vụ vi mô bản địa là đám mây. Phát triển lưu trữ dữ liệu phụ trợ luồng dữ liệu với PostgreSQL, ES, Apache Kafka và các công cụ dữ liệu đám mây khác nhau. Dịch vụ kiểm tra và triển khai các ứng dụng Dịch vụ và (Micro-) (Micro-) trên AWS EKS/Kubernetes với Bộ công cụ Docker. Cải thiện hệ thống hiện tại: Sửa đổi, cập nhật, tái cấu trúc và gỡ lỗi mã. Giám sát và tối ưu hóa hiệu suất hệ thống, giải quyết mọi vấn đề khi chúng phát sinh. Phát triển tài liệu trong suốt vòng đời phát triển phần mềm (SDLC). Phục vụ như một chuyên gia về hệ thống và cung cấp hỗ trợ kỹ thuật cho các nhóm nội bộ khác.",
    "Kiến trúc sư, xây dựng và duy trì các dịch vụ phụ trợ có thể mở rộng và API REST bằng các mẫu .NET Core, ASP.NET và Microservice. Thiết kế các mô hình dữ liệu được tối ưu hóa và các chiến lược ORM (Framework, SQL Server) và quản lý các hệ thống tin nhắn NoQuery, bộ nhớ đệm và nhắn tin. Tích hợp các giải pháp bản địa trên đám mây với Docker/Kubernetes, CI/CD (Azure DevOps, GitHub Action) và điều phối container. Đánh giá thiết kế chính, tiêu chuẩn mã hóa và thực hiện kiểm tra đơn vị/tích hợp/duy trì thực hành mã sạch. Các kỹ sư cố vấn trong chương trình đồng thời, không đồng bộ, CQRS, tìm nguồn cung ứng sự kiện, nhận dạng/auth và các mẫu thiết kế. Thúc đẩy nghiên cứu kỹ thuật để đề xuất hiệu suất, bảo mật và cải thiện khả năng sử dụng. Chủ động tham gia vào phân tích yêu cầu, hợp tác với chủ sở hữu sản phẩm và chuyển thành các giải pháp mạnh mẽ.",
    "Tham gia phát triển hệ thống phần mềm giao dịch chứng khoán tại thị trường chứng khoán Việt Nam. Phát triển các tính năng mới, cải tiến và nâng cấp các tính năng nhằm đáp ứng được các nhu cầu nghiệp vụ. Phối hợp cùng đội ngũ BA phân tích, thiết kế, đưa ra giải pháp để phát triển dự án phần mềm. Tham gia triển khai các dự án phát triển phần mềm.",
    "Phát triển và bảo trì các ứng dụng web backend sử dụng PHP Framework Laravel. Thiết kế, xây dựng và tối ưu hóa cơ sở dữ liệu (MySQL, PostgreSQL, hoặc MongoDB). Phối hợp với nhóm frontend để tích hợp API và đảm bảo tính năng hoạt động mượt mà. Phân tích yêu cầu dự án, đưa ra giải pháp kỹ thuật và tham gia vào quá trình phát triển phần mềm. Đảm bảo mã nguồn đáp ứng các tiêu chuẩn về chất lượng, bảo mật, và hiệu năng. Thực hiện kiểm tra, sửa lỗi và cập nhật tính năng dựa trên yêu cầu từ khách hàng hoặc quản lý. Nghiên cứu và áp dụng các công nghệ mới để cải thiện hiệu suất và nâng cao chất lượng sản phẩm.",
    "Chịu trách nhiệm lập trình phần mềm, phát triển công cụ, ứng dụng để có thể cấu hình tích hợp nhiều ứng dụng khác nhau của khách hàng hoặc nội bộ. Tham gia vào các công đoạn khác của phát triển phần mềm từ thiết kế kiến trúc hệ thống, DB, kiến trúc tích hợp, phát triển, triển khai, tích hợp hệ thống. Phân tích và tùy chỉnh mã nguồn n8n (Node.JavaScript, TypeScript) theo yêu cầu nghiệp vụ. Chịu trách nhiệm tư vấn thiết kế và triển khai các giải pháp về Tích hợp hệ thống (System Integration) cho khách hàng doanh nghiệp và tổ chức viễn thông. Đánh giá, Tích hợp Tối ưu các thành phần phù hợp vào hệ thống tổng thể đáp ứng cho các yêu cầu vận hành và quản lý của khách hàng. Thực hiện các công việc khác theo yêu cầu của TBP.",
    "Phát triển các ứng dụng Web application/Mobile application/3D Web Viewer chủ yếu dựa trên các công nghệ về React.js, APS.NET/NestJS, SQL, MogoDB Xây dựng các hệ thống chuyển đổi số trong ngành Xây dựng và BIM/ CIM Nhật Bản. Bảo trì, cập nhật, nâng cấp các ứng dụng theo yêu cầu của khách hàng. Xây dựng báo cáo, hỗ trợ các phòng ban theo yêu cầu.",
    "Thiết kế, phát triển và tăng cường các chương trình phần mềm nội bộ dựa trên các yêu cầu từ các bộ phận khác nhau, đảm bảo phân phối kịp thời và chất lượng cao. Phối hợp với BA, nhóm cốt lõi, nhóm phát triển và FSS để phát triển các giải pháp kỹ thuật, dữ liệu truy cập và xử lý, các tính năng phần mềm kiểm tra và áp dụng các bản cập nhật hoặc bản vá hệ thống. Quản lý và duy trì các ứng dụng phần mềm và dịch vụ phần mềm trung gian được tích hợp với các hệ thống chứng khoán cốt lõi. Cung cấp hỗ trợ nhanh chóng cho người dùng cuối bằng cách xác định và giải quyết các vấn đề liên quan đến phần mềm để đảm bảo các hoạt động kinh doanh không bị gián đoạn. Tham gia vào các dự án phát triển phần mềm khác theo sự phân công của Giám đốc CNTT.",
    "Chúng tôi đang xây dựng một hệ thống dữ liệu thời gian thực để phục vụ nền tảng AI tài chính. Nhiệm vụ của bạn là kiến tạo nền móng kỹ thuật để thu thập, xử lý và truy vấn hàng triệu dữ liệu tin tức từ báo chí, mạng xã hội, diễn đàn... Hệ thống sẽ cung cấp thông tin ngữ cảnh theo thời gian thực cho AI tóm tắt và trả lời câu hỏi về từng mã cổ phiếu, hỗ trợ nhà đầu tư ra quyết định nhanh chóng và chính xác.",
    "Tham gia xây dựng và phát triển các dự án của Công ty; Tham gia phân tích, thiết kế, phát triển và vận hành, bảo trì ứng dụng. Hỗ trợ đối tác và các phòng ban khác; Công việc sẽ được trao đổi cụ thể hơn trong quá trình phỏng vấn.",
    "Viết tài liệu thiết kế chi tiết, thiết kế CSDL. Thiết kế được các module thành phần, các chức năng chi tiết theo kiến trúc đã có sẵn. Tích hợp mã nguồn (merge code), tích hợp hệ thống. Thực hiện các nhiệm vụ sửa lỗi được phát hiện trong quá trình phát triển và triển khai. Lập trình các chức năng được giao theo tài liệu giải pháp chi tiết. Viết tài liệu Hướng dẫn cài đặt, vận hành, khai thác. Thực hiện upcode các yêu cầu nâng cấp của dự án. Viết và thực hiện unit test. Thực hiện các công việc khác theo yêu cầu của Manager.",
    "Phát triển và duy trì các ứng dụng web sử dụng Node.JavaScript và các framework liên quan như NestJS. Tham gia toàn bộ vòng đời phát triển phần mềm: thiết kế, phát triển, kiểm thử, triển khai và bảo trì. Xây dựng và tối ưu hệ thống Message Queue đảm bảo luồng dữ liệu hoạt động ổn định. Quản lý và tối ưu cơ sở dữ liệu PostgreSQL hoặc MongoDB. Tích hợp các dịch vụ bên ngoài thông qua API. Phối hợp chặt chẽ với các bộ phận liên quan để đảm bảo sản phẩm đạt chất lượng cao. Nghiên cứu và ứng dụng công nghệ mới để cải thiện hiệu suất hệ thống. Thực hiện các công việc khác theo yêu cầu của trưởng nhóm và cấp trên.",
    "Phát triển các hệ thống phụ trợ với các trách nhiệm sau: Phân tích yêu cầu, thiết kế, mã hóa, kiểm tra tích hợp, triển khai, sửa đổi, sửa đổi mã nguồn, đánh giá mã, sửa lỗi.",
    "Chúng tôi đang tìm kiếm một thực tập sinh của nhà phát triển web, người đam mê phát triển PHP và WordPress. Bạn sẽ làm việc chặt chẽ với nhóm web của chúng tôi để hỗ trợ các tác vụ phát triển, bảo trì và tối ưu hóa trang web - chủ yếu sử dụng WordPress. Trách nhiệm: Hỗ trợ phát triển và tùy chỉnh các trang web bằng WordPress và PHP. Hỗ trợ xây dựng hoặc sửa đổi các chủ đề và plugin. Làm việc với HTML, CSS, JavaScript để thực hiện các cải tiến UI/UX. Khắc phục sự cố và khắc phục các lỗi nhỏ hoặc các vấn đề bố cục. Hỗ trợ cập nhật nội dung và kiểm tra cho các trang web. Hợp tác với các nhà thiết kế, nhà văn nội dung và nhà phát triển khi cần thiết.",
    "Mô tả về công việc: Triển khai các ứng dụng BPM và CRM cho lĩnh vực tài chính/ngân hàng. Vai trò Java Backend tập trung vào phát triển, tích hợp, và triển khai các ứng dụng BPM và CRM trong một hệ thống doanh nghiệp (triển khai cho Bank) sử dụng các công nghệ như Java, Spring Boot, BPMN 2.0, và các thành phần cơ sở dữ liệu/message broker (MySQL, PostgreSQL, Apache Kafka, v.v.). Công việc bao gồm thiết kế quy trình nghiệp vụ (BPM), quản lý quan hệ khách hàng (CRM), tối ưu hiệu suất, bảo mật, và triển khai trên môi trường containerized (Docker, Kubernetes).",
    "Phát triển, tối ưu các chức năng hệ thống backend theo sự phân công và định hướng từ PM hoặc Leader. Tham gia phân tích nghiệp vụ, phân rã chức năng, phân tích hệ thống, kiểm thử logic và trải nghiệm, sửa lỗi, triển khai hệ thống. Chịu trách nhiệm về chất lượng và hiệu quả code của các module được giao. Đảm bảo sản phẩm backend ổn định, hiệu suất tốt và dễ bảo trì. Hợp tác chặt chẽ với các team liên quan (FE, QA, BA, DevOps...) để đảm bảo tiến độ và chất lượng sản phẩm. Tham gia vào quy trình kiểm thử, fix bugs, triển khai và bảo trì hệ thống. Chủ động tìm hiểu nghiệp vụ và tham gia đề xuất cải tiến sản phẩm. Hỗ trợ các thành viên junior khi cần và có thể review code nếu được giao. Báo cáo tiến độ, vấn đề, kết quả công việc đến quản lý trực tiếp. Trải nghiệm sản phẩm định kỳ để hiểu hành vi người dùng, từ đó đưa ra các đề xuất cải tiến.",
    "Tham gia thiết kế, phát triển và bảo trì hệ thống web theo kiến trúc Microservices như hệ thống ERP, BOC, HRM phục vụ quản lý và điều hành doanh nghiệp. Phát triển frontend bằng Angular, tối ưu trải nghiệm người dùng (UI/UX). Phát triển backend bằng Spring Boot, tích hợp với Oracle và các dịch vụ nội bộ. Triển khai hệ thống sử dụng Docker. Tích hợp MongoDB, Redis và xử lý log tập trung với ELK Stack (Elasticsearch, Logstash, Kibana). Làm việc với các dịch vụ Google như Firebase, Google APIs, GenAI,... Phối hợp chặt chẽ với team QA, BA, DevOps trong quy trình Agile/Scrum.",
    "_Quy trình tuyển dụng:_ [1] Screen CV [2] Test chuyên môn (Offline) [3] Phỏng vấn (Offline) \n_Nội dung công việc:_",
    "Tuỳ theo nhu cầu dự án tại từng thời điểm hiện tại, công ty sẽ đào tạo những ngôn ngữ lập trình khác nhau và các kỹ thuật mới nhất, cụ thể như:+ Ngôn ngữ lập trình PHP với các framework phiên bản mới nhất.+ Kỹ thuật về OOP, PHP Basic, Database, ...+ Frontend và các framework như Vue.js, React.js, ...- Nắm bắt nghiệp vụ phân tích để phát triển hệ thống trên nền web cùng với các kỹ sư tại Việt Nam và tại Nhật Bản.",
    "Phát triển sản phẩm phần mềm trên nền tảng Java Strust .cho các đối tượng khác nhau. Tham gia vào các giai đoạn của dự án: Phân tích, thiết kế, lập trình, bảo trì phần mềm. Lập trình các module theo thiết kế và công việc được phân công. Tài liệu hóa các đặc tả thiết kế và chức năng.",
    "- Phát triển hệ thống Backend bằng ngôn ngữ Go và Node.JavaScript",
    "Phối hợp với Product và Frontend để xây dựng, thử nghiệm và triển khai các tính năng.",
    "Thiết kế hệ thống có tính mở rộng, hiểu suất cao, bảo mật.",
    "Viết code sạch, dễ bảo trì; xây thư viện dùng chung và tài liệu kỹ thuật",
    "1. Nghiên cứu và phát triển sản phẩm \n Phối hợp với BA để đưa ra bản thiết kế phần mềm \n Thiết kế DB, lên giải pháp thi công, luồng xử lý, xây dựng và triển khai các giải pháp phần mềm \n Viết các tài liệu kỹ thuật liên quan đến dự án \n Kiểm tra chất lượng sản phẩm, tự thực hiện các Test-case bắt buộc trước khi chuyển giao cho Tester \n Sửa lỗi và hỗ trợ các thành viên trong nhóm",
    "Phối hợp với Phòng Triển khai phần mềm để triển khai khách hàng mới và Phòng Hỗ trợ khách hàng để hỗ trợ, bảo trì sản phẩm",
    "Tham gia xây dựng hệ thống phần mềm do công ty phát triển. Phối hợp làm việc nhóm để hoàn thành công việc đúng quy trình và kế hoạch. Chủ động ước lượng và kiểm soát công việc, báo cáo công việc cho cấp trên. Tham gia nghiên cứu góp ý và chia sẻ giúp cải thiện chất lượng sản phẩm.",
    "- Tham gia phát triển, duy trì và nâng cấp các hệ thống phần mềm dựa trên nền tảng .NET (ASP.NET MVC, .NET Core).",
    "Thiết kế, xây dựng và triển khai API Web và các dịch vụ REST API.",
    "Hợp tác trong việc phân tích các yêu cầu, thiết kế hệ thống và đề xuất các giải pháp kỹ thuật.",
    "Làm việc với SQL Server: Viết truy vấn, tối ưu hóa hiệu suất và tạo các quy trình được lưu trữ.",
    "Hợp tác với các thành viên trong nhóm để đảm bảo các thời gian dự án và chất lượng sản phẩm.",
    "Gỡ lỗi, khắc phục sự cố và tối ưu hóa hiệu suất hệ thống.",
    "Thực hiện các tác vụ khác theo sự phân công của người quản lý.",
    "Phối hợp với các kỹ sư cao cấp để thiết kế, phát triển và duy trì các dịch vụ phụ trợ và API bằng Java hoặc Node.JavaScript. Viết mã sạch, hiệu quả và được ghi chép rõ ràng tuân thủ các tiêu chuẩn mã hóa của chúng tôi. Tham gia đánh giá mã, cung cấp và nhận phản hồi mang tính xây dựng để đảm bảo chất lượng mã. Hỗ trợ khắc phục sự cố, gỡ lỗi và tối ưu hóa hiệu suất ứng dụng. Tìm hiểu và áp dụng các thực tiễn tốt nhất trong tích hợp cơ sở dữ liệu (SQL và/hoặc NoQuery) và mô hình dữ liệu. Công việc hiệu quả trong một phương pháp phát triển nhanh (Scrum/Kanban). Sử dụng các hệ thống kiểm soát phiên bản, chủ yếu là GIT, để phát triển hợp tác. Đóng góp cho các cuộc thảo luận kỹ thuật và hỗ trợ nhóm trong việc phân tích các yêu cầu cho các tính năng mới.",
    "1. Phát triển các dự án lớn HA (High Availability), HP (High Performance), web application cho khách hàng Nhật Bản và Âu Mỹ. 2. Tham gia phát triển, tối ưu và bảo trì các hệ thống web applications đã có, bao gồm cả front-end và back-end. 3. Viết unit test, fix bugs để đảm bảo chất lượng đầu ra của sản phẩm. 4. Viết tài liệu cho dự án. 5. Nghiên cứu, tìm hiểu, cập nhật và áp dụng các công nghệ mới để tăng chất lượng dự án.",
    "Tham gia phát triển phần mềm theo quy trình Agile/Scrum. Tiếp nhận yêu cầu bài toán từ khách hàng, viết tài liệu phân tích yêu cầu, đặc tả yêu cầu, thiết kế chi tiết, thiết kế CSDL. Được đào tạo công nghệ và thực chiến qua các dự án lớn. Chủ động và phối hợp đồng nghiệp và đối tác hoàn thành các việc được giao. Nghiên cứu, tìm kiếm, đề xuất các giải pháp/sáng kiến CNTT.",
    "Phát triển/ triển khai các yêu cầu của ứng dụng Core bảo hiểm. Phối hợp với BA tiếp nhận yêu cầu từ các phòng ban thuộc Khối nghiệp vụ. Lập trình và triển khai chương trình đáp ứng yêu cầu người dùng. Làm việc với QA (Quality Assurance) để giải quyết các lỗi phát sinh trong quá trình phát triển. Các công việc phát sinh khác theo yêu cầu của lãnh đạo.",
    "Phát triển, bảo trì các ứng dụng Web Backend sử dụng Java (Spring MVC / Spring Boot / Servlet). Thiết kế API theo yêu cầu của khách hàng, đảm bảo đúng chức năng nghiệp vụ và dễ dàng tích hợp với các hệ thống bên ngoài. Phân tích yêu cầu, đọc hiểu tài liệu kỹ thuật chuyên ngành (tiếng Anh) từ khách hàng hoặc đối tác. Thiết kế mô hình dữ liệu, luồng xử lý và kiến trúc hệ thống theo yêu cầu. Tích hợp thư viện hoặc SDK do nhà sản xuất thiết bị cung cấp (ví dụ: thiết bị phần cứng chuyên dụng như HSM, Trident,...). Viết tài liệu kỹ thuật, tài liệu mô hình hóa hệ thống. Phối hợp với nhóm Frontend, BA và QA để đảm bảo tiến độ và chất lượng sản phẩm.",
    "Tham gia nghiên cứu và phát triển các dự án tại các công ty con, công ty thành viên của Tập Đoàn như module HRM, module quản lý công việc, module quản lý khách sạn, website, .... Đọc và phân tích tài liệu yêu cầu chức năng từ khách hàng (là các phòng ban/bộ phận/công ty con/thành viên của Tập Đoàn) để đảm bảo hiểu rõ và đáp ứng chính xác. Viết tài liệu thiết kế chi tiết, thực hiện coding và unit test với các dự án công nghệ. Đã làm việc với: .NET MVC Core, C#, Entity Framework, LINQ, Web API. Đã làm việc với: HTML, CSS, JavaScript, JQuery, Bootstrap, ... Đã từng làm với ít nhất một Database: SQL Server, MySQL, Oracle... Biết thiết kế CSDL theo các dạng chuẩn (SQL) hoặc NoSQL. Sử dụng được tool quản lý source code như: Git, ... Đọc hiểu tài liệu tiếng Anh chuyên ngành. Không ngừng nghiên cứu và học hỏi công nghệ mới để nâng cao kỹ năng và năng suất làm việc. Được hỗ trợ và hướng dẫn bởi các thành viên khác trong nhóm phát triển. Tham gia nhiều dự án khác theo yêu cầu của quản lý và Project Manager (PM). Phối hợp với các bộ phận BA, Tester, UI/UX để phân tích yêu cầu và triển khai tính năng mới. Xây dựng, cải tiến các module trong hệ thống ERP như: HRM, CRM, Account, DMS, ... và các module nghiệp vụ khác theo định hướng phát triển của Tập Đoàn; Đã nghiên cứu việc xử lý dữ liệu lớn, tối ưu truy vấn SQL và hiệu năng hệ thống là một lợi thế. Làm việc theo mô hình Agile/Scrum, đảm bảo tiến độ và chất lượng phần mềm. Soạn thảo và cập nhật tài liệu kỹ thuật, bao gồm tài liệu thiết kế và hướng dẫn sử dụng. Phân tích và làm rõ các yêu cầu về phần mềm của đơn vị sử dụng. Phân tích và đưa ra mô hình lược đồ dựa trên yêu cầu đã thu thập được. Viết các tài liệu đặc tả yêu cầu nghiệp vụ phần mềm, tài liệu đặc tả trường hợp sử dụng (usecase); thiết kế giao diện mẫu (prototype), kiểm thử phần mềm (testcase). Tư vấn trên góc độ nghiệp vụ dựa vào các phân tích và nghiên cứu của mình. Truyền đạt thông tin nội dung, kiểm tra, giám sát, kiểm thử nghiệm thu chất lượng, tính năng phần mềm. Tài liệu hóa hướng dẫn hệ thống, quy trình, tác vụ. Tổ chức hướng dẫn, hỗ trợ cho người dùng sử dụng sản phẩm và xử lý sự cố khi vấn đề xảy ra. Quản lý thay đổi theo yêu cầu và đảm bảo rằng yêu cầu được cập nhật theo thay đổi.",
    "MỤC ĐÍCH CỦA VỊ TRÍ NÀY:",
    "Tham gia thiết kế, xây dựng và triển khai các hệ thống back-end cho nền tảng Vinbase",
    "Tham gia thiết kế, xây dựng và bàn giao các dự án phát triển Trợ lý ảo triển khai trên nền tảng Vinbase \n \nTRÁCH NHIỆM CỦA VỊ TRÍ NÀY:",
    "Thiết kế giải pháp và triển khai các hệ thống, sản phẩm AI, Machine Learning có khả năng co giãn, luôn luôn sẵn sàng và có khả năng chịu lỗi.",
    "Phát triển sản phẩm phần mềm có khả năng tích hợp hiệu quả và an toàn đến các nền tảng và đối tác bên thứ 3.",
    "Tham gia và tuân thủ các quy trình phát triển phần mềm linh hoạt, thực hành DevOps, CI/CD để phát triển và triển khai phần mềm với tốc độ cao nhất.",
    "Hướng dẫn các thành viên ít kinh nghiệm hơn, chủ động đóng góp và thực hiện các ý tưởng để cải thiện chất lượng sản phẩm, hiệu suất làm việc của nhóm và môi trường làm việc trong công ty.",
    "Các công việc khác theo phân công của cấp trên."
  ],
  "jd_count": 100,
  "_parent": "cong_nghe_thong_tin_ky_thuat_so",
  "_parent_display": "Công nghệ thông tin",
  "_sub_occupation": "backend_developer",
  "_sub_display": "Lập trình viên Backend",
  "_meta": {
    "jd_count": 100,
    "core_skill_count": 22,
    "optional_skill_count": 131,
    "built_at": "2026-06-22T17:32:57",
    "granularity": "sub_occupation",
    "embedding_dim": 768,
    "embedding_model": "gte_multilingual_resume_match"
  },
  "embedding": [
    -0.041753530502319336,
    -0.0054955193772912025,
    -0.004082719795405865,
    0.03962160274386406,
    -0.010904647409915924,
    -0.032773494720458984,
    -0.08198299258947372,
    0.007348733954131603,
    0.03833061084151268,
    -0.01902223378419876,
    -0.04611128196120262,
    -0.020519720390439034,
    -0.09780943393707275,
    0.03615262359380722,
    -0.04010847583413124,
    0.03579516336321831,
    0.07940990477800369,
    -0.026020746678113937,
    0.008676690049469471,
    -0.006019556429237127,
    0.07108298689126968,
    0.04500902071595192,
    -0.0037050489336252213,
    -0.0348222479224205,
    0.023418383672833443,
    0.028824277222156525,
    0.002120871329680085,
    -0.07628153264522552,
    -0.09019642323255539,
    0.06327587366104126,
    -0.011875797994434834,
    -0.06768257170915604,
    0.00017558391846250743,
    0.03062814101576805,
    0.011497162282466888,
    -0.037772879004478455,
    0.03950956091284752,
    -0.0025802068412303925,
    -0.015124931931495667,
    0.008197731338441372,
    -0.010590706020593643,
    -0.06321531534194946,
    -0.004985691048204899,
    -0.0011508413590490818,
    0.007769463118165731,
    0.03861702233552933,
    -0.045999929308891296,
    0.04433552548289299,
    0.007524318993091583,
    0.01408507488667965,
    0.03020293079316616,
    0.016201592981815338,
    0.06957828998565674,
    0.03285624459385872,
    0.01263721939176321,
    -0.058624267578125,
    -0.12485365569591522,
    -0.03635308891534805,
    0.08295686542987823,
    -0.050620414316654205,
    -0.007550785783678293,
    -0.00578273506835103,
    -0.010507296770811081,
    0.008790059015154839,
    -0.00299814622849226,
    -0.07191041111946106,
    0.05869915336370468,
    -0.0341356135904789,
    0.1300290822982788,
    0.051210302859544754,
    -0.02055525965988636,
    0.013276435434818268,
    -0.007604336831718683,
    -0.005569873843342066,
    0.008152900263667107,
    0.04285294562578201,
    -0.019024237990379333,
    0.013150334358215332,
    0.05811665579676628,
    0.016566935926675797,
    0.018332161009311676,
    0.016863590106368065,
    0.009363744407892227,
    -0.003299360629171133,
    -0.0410800576210022,
    -0.026707712560892105,
    0.003182261250913143,
    -0.04757915064692497,
    -5.12668475494138e-06,
    0.0064383698627352715,
    0.03899116441607475,
    -0.0007333677494898438,
    0.03191157802939415,
    0.03187735751271248,
    0.022883281111717224,
    0.04406452178955078,
    -0.007005984894931316,
    0.03631522133946419,
    0.021140459924936295,
    -0.006971497088670731,
    0.041539356112480164,
    0.021140847355127335,
    0.03542766347527504,
    0.011089681647717953,
    -0.00948308315128088,
    -0.030322687700390816,
    0.004562860354781151,
    -0.009792493656277657,
    -0.04015466943383217,
    0.0057032303884625435,
    -0.034424830228090286,
    0.014252924360334873,
    -0.055054228752851486,
    -0.0008020756649784744,
    -0.00010846866643987596,
    0.0372568741440773,
    0.060559745877981186,
    -0.02918844483792782,
    0.04631885141134262,
    0.06669590622186661,
    -0.016352910548448563,
    -0.020039469003677368,
    0.00869758427143097,
    -0.022844452410936356,
    -0.12617643177509308,
    0.005153720732778311,
    0.0012890917714685202,
    -0.030765922740101814,
    -0.024788077920675278,
    -0.00479169050231576,
    0.04269484058022499,
    0.022743970155715942,
    0.05487781763076782,
    -0.057066358625888824,
    -0.04559403285384178,
    0.01148916780948639,
    0.008449854329228401,
    0.07970646023750305,
    0.032292068004608154,
    -0.01062983088195324,
    -0.06990604847669601,
    0.016914302483201027,
    -0.0768962949514389,
    0.020627209916710854,
    0.009010807611048222,
    0.03779352456331253,
    -0.05006551370024681,
    -0.07003923505544662,
    0.015180299058556557,
    0.01909167319536209,
    -0.0023922796826809645,
    0.0103598115965724,
    0.061633288860321045,
    0.0803096666932106,
    0.024075878784060478,
    0.005284707993268967,
    -0.005985948722809553,
    0.06307780742645264,
    -0.006514690816402435,
    -0.013482267037034035,
    0.07237504422664642,
    0.062395282089710236,
    0.0026623988524079323,
    -0.011989769525825977,
    -0.0007697984110563993,
    -0.004058887716382742,
    0.02168569341301918,
    0.01862243562936783,
    -0.011577306315302849,
    0.0007241980638355017,
    -0.06158816069364548,
    0.04403645545244217,
    0.03138116002082825,
    -0.0038393656723201275,
    -0.017541225999593735,
    0.03886202350258827,
    -0.0005347288679331541,
    0.016867758706212044,
    0.024952976033091545,
    0.014408238232135773,
    0.023158540949225426,
    -0.030887823551893234,
    -0.00838420819491148,
    -0.03976515680551529,
    0.04101582616567612,
    -0.021432697772979736,
    0.01478313747793436,
    -0.0388820506632328,
    0.01674620993435383,
    0.04384028539061546,
    -0.015111055225133896,
    0.012285733595490456,
    -0.10309118777513504,
    0.008516320027410984,
    -0.033904969692230225,
    -0.05949431657791138,
    0.006740835029631853,
    0.030918532982468605,
    -0.017144586890935898,
    0.02298642136156559,
    0.06568413227796555,
    -0.006194188725203276,
    -0.005659192334860563,
    0.04736407846212387,
    -0.04845640808343887,
    0.0266819279640913,
    0.017939595505595207,
    -0.014178317971527576,
    -0.029676374047994614,
    -0.05079004913568497,
    0.007024258375167847,
    0.009131566621363163,
    -0.016127677634358406,
    -0.00569279445335269,
    -0.03194749727845192,
    -0.04032520577311516,
    -0.06814762949943542,
    -0.035709038376808167,
    0.04203644394874573,
    -0.013210573233664036,
    -0.0063161286525428295,
    -0.02747609093785286,
    -0.006262447219341993,
    0.005321861710399389,
    -0.007140910718590021,
    0.02332242578268051,
    -0.008969459682703018,
    0.02082611434161663,
    0.009746621362864971,
    -0.025534046813845634,
    -0.009760234504938126,
    -0.033866915851831436,
    0.0373527854681015,
    -0.03369174897670746,
    0.010528760962188244,
    -0.03224826976656914,
    0.02475927211344242,
    0.030214188620448112,
    -0.025544991716742516,
    0.03801896795630455,
    0.02514789253473282,
    0.020594406872987747,
    0.028715433552861214,
    0.017550945281982422,
    0.03589176386594772,
    -0.043712906539440155,
    -0.00786474160850048,
    -0.016458339989185333,
    -0.018256807699799538,
    0.010092654265463352,
    0.010552704334259033,
    0.04167135804891586,
    -0.0334167443215847,
    0.03932788595557213,
    0.0010580825619399548,
    -0.043320976197719574,
    -0.012972821481525898,
    -0.017187360674142838,
    0.03549279645085335,
    -0.04422943294048309,
    -0.016167979687452316,
    -0.002552705118432641,
    0.043663542717695236,
    -0.035522013902664185,
    0.038334641605615616,
    -0.13938601315021515,
    0.010052500292658806,
    0.01581823267042637,
    -0.0146549167111516,
    0.0030858085956424475,
    -0.011517736129462719,
    -0.03106120228767395,
    -0.03205849602818489,
    0.028747128322720528,
    -0.016204042360186577,
    -0.007621777709573507,
    -0.01812736503779888,
    -0.00474699167534709,
    0.03912287577986717,
    -0.019639020785689354,
    0.019815944135189056,
    0.01361743826419115,
    -0.02102062478661537,
    -0.056059543043375015,
    -0.028205297887325287,
    0.03348180651664734,
    0.032095178961753845,
    0.010708557441830635,
    -0.006921428255736828,
    0.041403889656066895,
    -0.025875480845570564,
    -0.034517593681812286,
    0.019037436693906784,
    0.0020751163829118013,
    0.02858574129641056,
    0.026366369798779488,
    -0.06307040899991989,
    0.03235767036676407,
    0.011958842165768147,
    -0.0288770142942667,
    -0.05642054229974747,
    -0.02010444924235344,
    0.024435603991150856,
    0.013026891276240349,
    -0.04882924258708954,
    -0.024327026680111885,
    -0.06942134350538254,
    0.015920443460345268,
    -0.0036658113822340965,
    0.04551345482468605,
    0.005661091301590204,
    0.022649113088846207,
    0.04325688257813454,
    -0.020801810547709465,
    0.02071065455675125,
    -0.005018011201173067,
    0.016683360561728477,
    0.02826634980738163,
    -0.044338520616292953,
    0.03182145953178406,
    -0.0031955086160451174,
    0.08744975179433823,
    0.02830755151808262,
    0.017291270196437836,
    -0.026542456820607185,
    -0.027384253218770027,
    -0.012173105962574482,
    0.041646093130111694,
    -0.0209280364215374,
    -0.012362184002995491,
    -0.021636072546243668,
    0.000965111015830189,
    0.011213167570531368,
    -0.08055365830659866,
    0.007449138443917036,
    -0.013425406999886036,
    0.019999908283352852,
    0.02931775338947773,
    0.005499479826539755,
    0.02023552916944027,
    -0.028922371566295624,
    0.03356073796749115,
    -0.10175417363643646,
    -0.007246790919452906,
    0.012900544330477715,
    -0.052764084190130234,
    -0.005262349266558886,
    -0.017428571358323097,
    0.01707478053867817,
    -0.012373017147183418,
    0.024383587762713432,
    0.002278092550113797,
    0.001305317971855402,
    0.028828497976064682,
    0.015586980618536472,
    -0.013239467516541481,
    0.011987137608230114,
    0.0033834457863122225,
    0.018461765721440315,
    0.04646614193916321,
    -0.006909862160682678,
    0.0015506106428802013,
    0.018482167273759842,
    0.004037813283503056,
    0.01555910985916853,
    -0.01516778115183115,
    -0.008649650029838085,
    -0.007491252385079861,
    -0.04337232932448387,
    0.02167474664747715,
    0.046207863837480545,
    0.04643693193793297,
    0.00712187122553587,
    0.09406577795743942,
    -0.0037095053121447563,
    0.07733190804719925,
    0.01517412904649973,
    -0.004919497296214104,
    0.011541338637471199,
    -0.01395931001752615,
    0.02046375907957554,
    -0.013054881244897842,
    0.027938788756728172,
    0.01233670487999916,
    -0.015904344618320465,
    -0.01611218973994255,
    -0.029365723952651024,
    -1.1625689694483299e-05,
    -0.004696300253272057,
    -0.0005499244434759021,
    7.117178029147908e-05,
    -0.00027112255338579416,
    -0.04944030940532684,
    0.037480875849723816,
    0.0687316283583641,
    0.030276542529463768,
    0.04827804118394852,
    0.02488822303712368,
    -0.01592768356204033,
    0.03758913651108742,
    0.02550446428358555,
    -0.018207108601927757,
    -0.00945170596241951,
    0.00038943541585467756,
    0.042599599808454514,
    0.016447672620415688,
    -0.01906057447195053,
    -0.05115871503949165,
    -0.018762443214654922,
    -0.007703745737671852,
    0.03871013596653938,
    -0.00788545235991478,
    0.04534505307674408,
    -0.038209468126297,
    -0.024636415764689445,
    0.055137477815151215,
    0.0055363061837852,
    0.07947295159101486,
    0.2553330659866333,
    -0.05639542266726494,
    0.028800297528505325,
    0.05634372681379318,
    -0.00962301716208458,
    -0.03461761400103569,
    -0.015523310750722885,
    0.06207859516143799,
    -0.018303362652659416,
    -0.03651951625943184,
    -0.011927171610295773,
    0.03455427289009094,
    -0.005989613477140665,
    0.02123505435883999,
    0.025989683344960213,
    -0.06968667358160019,
    0.01982547901570797,
    0.018280738964676857,
    -0.0076017784886062145,
    -0.009430897422134876,
    0.018308771774172783,
    0.0012837410904467106,
    0.0015656835166737437,
    -0.01229238510131836,
    0.017601873725652695,
    0.004352902993559837,
    -0.02878514491021633,
    -0.03769400715827942,
    0.015282264910638332,
    0.009940612129867077,
    -0.02007313445210457,
    0.03348607197403908,
    -0.11761301010847092,
    0.018199024721980095,
    -0.023761792108416557,
    0.0031843336764723063,
    -0.009311847388744354,
    -0.0323200449347496,
    -0.034924671053886414,
    0.014780068770051003,
    -0.01665455847978592,
    -0.05605439841747284,
    -0.012342949397861958,
    0.00592409074306488,
    -0.04646513983607292,
    0.04922911897301674,
    0.013799096457660198,
    -0.031385261565446854,
    0.007793980184942484,
    0.008564085699617863,
    0.017462773248553276,
    0.01822797767817974,
    -0.0037826751358807087,
    0.04133670777082443,
    0.029891351237893105,
    -0.010774597525596619,
    -0.024108491837978363,
    0.002423971425741911,
    -0.027056552469730377,
    0.051516737788915634,
    0.025799460709095,
    -0.021478768438100815,
    0.03805328533053398,
    -0.00437816372141242,
    -0.015767540782690048,
    -0.04606202617287636,
    0.062036771327257156,
    0.039995305240154266,
    -0.0020920198876410723,
    -0.08899576216936111,
    0.01024634949862957,
    -0.020598193630576134,
    0.05343439429998398,
    0.09859628230333328,
    0.015471347607672215,
    -0.004237442277371883,
    0.003949962090700865,
    0.036873959004879,
    0.010212301276624203,
    0.013843117281794548,
    -0.023451466113328934,
    0.012467375956475735,
    -0.05724320560693741,
    -0.045928601175546646,
    -0.0029149341862648726,
    0.01803548075258732,
    0.006864133756607771,
    -0.010914468206465244,
    0.054444488137960434,
    -0.007005306426435709,
    0.013564885593950748,
    0.06800719350576401,
    -0.022556861862540245,
    0.008214953355491161,
    0.0658319890499115,
    -0.04597102850675583,
    0.018483856692910194,
    0.019773242995142937,
    -0.03294689580798149,
    0.005531443748623133,
    0.032057542353868484,
    -0.006927372422069311,
    0.006777968257665634,
    -0.010783829726278782,
    0.027820492163300514,
    0.006765199825167656,
    -0.01642485521733761,
    0.02826884016394615,
    0.016750440001487732,
    -0.0027802244294434786,
    -0.006312876474112272,
    -0.025684241205453873,
    0.00792889017611742,
    0.07438258081674576,
    0.007502258755266666,
    0.022965317592024803,
    0.028005516156554222,
    -0.006323438603430986,
    0.04159945622086525,
    0.03697974234819412,
    -0.022319436073303223,
    0.017455637454986572,
    -0.018174761906266212,
    0.01563667133450508,
    0.05446195229887962,
    -0.06417182087898254,
    0.0015403315192088485,
    0.028045959770679474,
    0.031210627406835556,
    -0.09403464198112488,
    -0.04572754725813866,
    -0.012707107700407505,
    -0.03229473903775215,
    0.055494993925094604,
    0.048764877021312714,
    0.0262489952147007,
    -0.03456386178731918,
    -0.018319666385650635,
    -0.011795008555054665,
    -0.01318822056055069,
    -0.01045753713697195,
    0.01103234849870205,
    -0.03213507682085037,
    -0.054447442293167114,
    -0.0076855882070958614,
    -0.027419494464993477,
    -0.00717170350253582,
    0.021403012797236443,
    -0.011490780860185623,
    0.010876853950321674,
    0.002015276812016964,
    0.03496318683028221,
    -0.012897538021206856,
    0.03339153900742531,
    0.02034553699195385,
    -0.025716019794344902,
    -0.0032591954804956913,
    -0.05065113306045532,
    -0.007955146953463554,
    -0.045184340327978134,
    -0.02691175602376461,
    -0.0037062959745526314,
    -0.10611321032047272,
    -0.026231680065393448,
    0.01788308098912239,
    -0.026635289192199707,
    -0.058273039758205414,
    0.014694186858832836,
    -0.04493642598390579,
    -0.002876098034903407,
    -0.03118663653731346,
    -0.0006019246648065746,
    -0.05330820754170418,
    0.004287471063435078,
    0.007160151842981577,
    -0.0017273616977036,
    -0.0019013932906091213,
    0.023194575682282448,
    0.00041672695078887045,
    0.0022799696307629347,
    -0.019744714722037315,
    -0.00027003983268514276,
    -0.013667026534676552,
    -0.0350605808198452,
    0.002556782914325595,
    -0.010048264637589455,
    0.04976886138319969,
    -0.026275042444467545,
    -0.02216940186917782,
    -0.03884449601173401,
    -0.020518960431218147,
    0.005083182360976934,
    0.003368914360180497,
    -0.01604079268872738,
    -0.018896255642175674,
    0.007708927616477013,
    -0.0030314482282847166,
    0.022801348939538002,
    -0.008543421514332294,
    -0.05680391564965248,
    -0.01868157647550106,
    0.03593480959534645,
    -0.0511578693985939,
    -0.0061869327910244465,
    -0.0034155002795159817,
    0.003980235196650028,
    -0.018729854375123978,
    0.03362976759672165,
    -0.0500347875058651,
    -0.010059143416583538,
    -0.062092375010252,
    -0.040410712361335754,
    -0.030800526961684227,
    0.015682535246014595,
    -0.0012287776917219162,
    -0.01864173635840416,
    -0.03109399601817131,
    -0.03585543856024742,
    -0.08421342819929123,
    -0.022868091240525246,
    -0.029233120381832123,
    0.014162076637148857,
    -0.04816805571317673,
    0.03891235962510109,
    0.0015648141270503402,
    -0.0017197434790432453,
    0.023169556632637978,
    0.006877984385937452,
    0.01252264715731144,
    0.024251535534858704,
    -0.01611480303108692,
    0.021427258849143982,
    -0.000613122305367142,
    0.010192952118813992,
    -0.0032849523704499006,
    0.010215183719992638,
    0.013001978397369385,
    -0.006345913279801607,
    -0.03176499903202057,
    -0.017183924093842506,
    0.0653860941529274,
    0.06305067241191864,
    0.011342131532728672,
    -0.0004929826245643198,
    0.06824696063995361,
    -0.027594448998570442,
    -0.04452656954526901,
    -0.029553264379501343,
    0.013653982430696487,
    0.03766471520066261,
    0.040936652570962906,
    -0.0020439999643713236,
    0.01204335130751133,
    -0.0036105080507695675,
    0.020899344235658646,
    0.06199224293231964,
    -0.018575267866253853,
    0.052773818373680115,
    -0.018095914274454117,
    -0.04155219346284866,
    -0.006009416654706001,
    0.049192164093256,
    0.03320027142763138,
    -0.03227117285132408,
    -0.008485732600092888,
    -0.009217310696840286,
    0.03511335700750351,
    -0.03238041698932648,
    -0.01707395352423191,
    0.003875189693644643,
    0.00745040038600564,
    -2.2573403839487582e-05,
    0.002087141154333949,
    0.00460417615249753,
    0.013398043811321259,
    0.025992177426815033,
    0.027203328907489777,
    -0.022558659315109253,
    0.008891861885786057,
    0.01730886660516262,
    -0.03871490806341171,
    -0.05220586806535721,
    0.007017580792307854,
    0.04831851273775101,
    0.0006828411715105176,
    0.017047535628080368,
    0.014723055996000767,
    -0.03208107873797417,
    0.006341574713587761,
    0.008288255892693996,
    0.00043788334005512297,
    0.03627881780266762,
    0.023605335503816605,
    0.010680186562240124,
    0.0816444531083107,
    -0.005689550191164017,
    -0.039014801383018494,
    -0.017516205087304115,
    -0.02086556889116764,
    0.03058302029967308,
    0.011704427190124989,
    0.16907404363155365,
    0.009877663105726242,
    0.007795036304742098,
    -0.031290002167224884,
    0.0001154612036771141,
    -0.009611021727323532,
    0.009801063686609268,
    0.05567463859915733,
    0.058266155421733856,
    0.011560950428247452,
    -0.009572269394993782,
    -0.020048638805747032,
    -0.011052185669541359,
    0.025150133296847343,
    0.04732539504766464,
    -0.007649165112525225,
    -0.06022699549794197,
    0.03127332404255867,
    -0.027344506233930588,
    0.011826025322079659,
    0.009370137006044388,
    0.024139443412423134,
    -0.008455079048871994,
    -0.03364008292555809,
    0.021517330780625343,
    -0.015552686527371407,
    0.026668468490242958,
    0.0612393282353878,
    0.10993489623069763,
    -0.023033104836940765,
    -0.00893388595432043,
    0.00027682085055857897,
    0.0321354977786541,
    -0.026348911225795746,
    0.04605972394347191,
    0.0938643217086792,
    0.025581438094377518,
    0.004320577252656221,
    0.022123850882053375,
    0.0011023329570889473,
    0.02103513665497303,
    -0.041818633675575256,
    -0.031244179233908653,
    0.022827591747045517,
    0.02975911647081375,
    -0.040106531232595444,
    0.010809243656694889,
    -0.0363348163664341,
    0.03148664906620979
  ]
}